shipswamy/__init__.py
shipswamy/core.py
shipswamy-0.0.7.dist-info/METADATA
shipswamy-0.0.7.dist-info/WHEEL
shipswamy-0.0.7.dist-info/RECORD
