Metadata-Version: 2.4
Name: shipswamy
Version: 0.0.7
Summary: A Python library to print long ML or GenAI programs.
Author-email: Adi <your-email@example.com>
License: MIT
Classifier: License :: OSI Approved :: MIT License
Classifier: Operating System :: OS Independent
Classifier: Programming Language :: Python :: 3
Requires-Python: >=3.8
